tutorial_package_VG/__init__.py
tutorial_package_VG/greet.py
tutorial_package_VG-0.0.1.dist-info/DESCRIPTION.rst
tutorial_package_VG-0.0.1.dist-info/METADATA
tutorial_package_VG-0.0.1.dist-info/RECORD
tutorial_package_VG-0.0.1.dist-info/WHEEL
tutorial_package_VG-0.0.1.dist-info/metadata.json
tutorial_package_VG-0.0.1.dist-info/top_level.txt
