Metadata-Version: 2.0
Name: tutorial-package-VG
Version: 0.0.1
Summary: An demonstration of how to create and publish python packages
Home-page: UNKNOWN
Author: Vendi Grobelsek
Author-email: UNKNOWN
License: BSD
Platform: UNKNOWN
